orca_agent_sdk/__init__.py
orca_agent_sdk/config.py
orca_agent_sdk/server.py
orca_agent_sdk-0.1.3.dist-info/licenses/LICENSE
orca_agent_sdk-0.1.3.dist-info/METADATA
orca_agent_sdk-0.1.3.dist-info/WHEEL
orca_agent_sdk-0.1.3.dist-info/top_level.txt
orca_agent_sdk-0.1.3.dist-info/RECORD
